local_ssh_config/__init__.py
local_ssh_config/__main__.py
local_ssh_config/_config.py
local_ssh_config/_constants.py
local_ssh_config/_echos.py
local_ssh_config/_version.py
local_ssh_config/cli.py
local_ssh_config/hosts/__init__.py
local_ssh_config/hosts/_constants.py
local_ssh_config/hosts/_update.py
local_ssh_config/py.typed
local_ssh_config/ssh/__init__.py
local_ssh_config/ssh/_constants.py
local_ssh_config/ssh/_update.py
local_ssh_config/ssh/structure.py
local_ssh_config/templates/config.d/config.j2
local_ssh_config/templates/config.j2
local_ssh_config/utils/__init__.py
local_ssh_config/utils/ip_addresses/__init__.py
local_ssh_config/utils/ip_addresses/_powershell.py
local_ssh_config/utils/ip_addresses/hyper_v.py
local_ssh_config/utils/ip_addresses/multipass.py
local_ssh_config/utils/jinja/__init__.py
local_ssh_config/utils/jinja/_constants.py
local_ssh_config/utils/jinja/_environment.py
local_ssh_config/utils/jinja/_helpers.py
local_ssh_config-0.4.5.dist-info/entry_points.txt
local_ssh_config-0.4.5.dist-info/LICENSE
local_ssh_config-0.4.5.dist-info/WHEEL
local_ssh_config-0.4.5.dist-info/METADATA
local_ssh_config-0.4.5.dist-info/RECORD
