Metadata-Version: 2.1
Name: local-ssh-config
Version: 0.4.5
Summary: Quickly update config (ssh files and host file) for your local virtual machines
Home-page: https://github.com/iancleary/local-ssh-config
License: MIT
Author: Ian Cleary
Author-email: contact@iancleary.me
Requires-Python: >=3.9,<4.0
Classifier: License :: OSI Approved :: MIT License
Classifier: Programming Language :: Python :: 3
Classifier: Programming Language :: Python :: 3.10
Classifier: Programming Language :: Python :: 3.9
Requires-Dist: Jinja2 (==3.1.2)
Requires-Dist: colorama (>=0.4.3,<0.5.0)
Requires-Dist: rich (>=10.11.0,<13.0.0)
Requires-Dist: shellingham (>=1.3.0,<2.0.0)
Requires-Dist: typer (==0.6.1)
